pyarbtools/__init__.py
pyarbtools/error.py
pyarbtools/gui.py
pyarbtools/instruments.py
pyarbtools/vsaControl.py
pyarbtools/wfmBuilder.py
pyarbtools-2025.6.1.dist-info/licenses/LICENSE
pyarbtools-2025.6.1.dist-info/METADATA
pyarbtools-2025.6.1.dist-info/WHEEL
pyarbtools-2025.6.1.dist-info/top_level.txt
pyarbtools-2025.6.1.dist-info/RECORD
