Metadata-Version: 2.4
Name: pyarbtools
Version: 2025.6.1
Summary: PyArbTools provides waveform creation and remote instrument control capabilities for Keysight signal generators.
Home-page: https://github.com/morgan-at-keysight/pyarbtools
Author: Morgan Allison
Author-email: morgan.allison@keysight.com
Classifier: Development Status :: 4 - Beta
Classifier: Intended Audience :: Developers
Classifier: Programming Language :: Python :: 3
Classifier: Programming Language :: Python :: 3.6
Classifier: Programming Language :: Python :: 3.7
Classifier: Programming Language :: Python :: 3.8
Classifier: Programming Language :: Python :: 3.9
Requires-Python: >=3.6
License-File: LICENSE
Requires-Dist: numpy
Requires-Dist: scipy
Requires-Dist: socketscpi
Requires-Dist: matplotlib
Requires-Dist: pyvisa
Dynamic: license-file
